{
  "version": 1,
  "dependencies": [
    {
      "source": {
        "git": {
          "remote": "https://github.com/anguslees/kustomize-libsonnet.git",
          "subdir": ""
        }
      },
      "version": "master"
    },
    {
      "source": {
        "git": {
          "remote": "https://github.com/prometheus-operator/kube-prometheus.git",
          "subdir": "jsonnet/kube-prometheus"
        }
      },
      "version": "release-0.7"
    },
    {
      "source": {
        "git": {
          "remote": "https://github.com/prometheus-operator/prometheus-operator.git",
          "subdir": "jsonnet/prometheus-operator"
        }
      },
      "version": "master"
    }
  ],
  "legacyImports": true
}
